datalibrary/__init__.py
datalibrary/datasetcollection.py
datalibrary/downloader.py
datalibrary/pipeline.py
datalibrary/s3Client.py
datalibrary/util.py
examples/__init__.py
pytdml/__init__.py
pytdml/convert_utils.py
pytdml/tdml_image_crop.py
pytdml/utils.py
pytdml/yaml_to_tdml.py
pytdml/io/S3_reader.py
pytdml/io/__init__.py
pytdml/io/internal.py
pytdml/io/tdml_readers.py
pytdml/io/tdml_writers.py
pytdml/ml/__init__.py
pytdml/ml/ml_operators.py
pytdml/ml/object_transforms.py
pytdml/ml/tdml_tensorflow.py
pytdml/ml/tdml_torch.py
pytdml/ml/tdml_torch_data_pipe.py
pytdml/type/__init__.py
pytdml/type/_utils.py
pytdml/type/basic_types.py
pytdml/type/basic_types_old.py
pytdml/type/extended_types.py
pytdml/type/extended_types_old.py
pytdml/type/test.py
tests/__init__.py
tests/test_basic_types.py
tests/test_tdml_io.py
pytdml-1.1.7.dist-info/LICENSE
pytdml-1.1.7.dist-info/METADATA
pytdml-1.1.7.dist-info/WHEEL
pytdml-1.1.7.dist-info/top_level.txt
pytdml-1.1.7.dist-info/RECORD
