Metadata-Version: 2.1
Name: pytdml
Version: 1.1.7
Summary: Parsing and encoding training datasets based on OGC Training Data Markup Language for AI (TrainingDML-AI) standard
Home-page: https://github.com/TrainingDML/pytdml
Author: Boyi Shangguan
Author-email: sgby@whu.edu.cn
License: MIT
Platform: UNKNOWN
Classifier: Development Status :: 3 - Alpha
Classifier: Intended Audience :: Developers
Classifier: Topic :: Scientific/Engineering :: GIS
Classifier: License :: OSI Approved :: MIT License
Classifier: Programming Language :: Python :: 3
License-File: LICENSE
Requires-Dist: dataclasses
Requires-Dist: geojson
